Metadata-Version: 2.1
Name: super-colored-print
Version: 0.0.3
Summary: Um pacote para facilitar a impressão de textos coloridos
Home-page: https://github.com/vitorStein/super-print-package
Author: Victor Stein
Author-email: victor.stein@outlook.com
License: UNKNOWN
Platform: UNKNOWN
Requires-Python: >=3.8
License-File: LICENSE
